{
  "version": 1,
  "files": [
    {
      "filePath": "core/crop-target-profile",
      "fileName": "profile.ts",
      "lineRange": { "start": 1, "end": 63 }
    },
    {
      "filePath": "core/crop-target-profile",
      "fileName": "types.ts",
      "lineRange": { "start": 1, "end": 53 }
    },
    {
      "filePath": "core/crop-target-profile",
      "fileName": "index.ts"
    },
    {
      "filePath": "core/crop-target-profile/__tests__",
      "fileName": "profile.test.ts"
    },
    {
      "filePath": "core/run-orchestrator",
      "fileName": "types.ts",
      "lineRange": { "start": 1, "end": 75 }
    },
    {
      "filePath": "core/run-orchestrator",
      "fileName": "bootstrap.ts",
      "lineRange": { "start": 1, "end": 80 }
    },
    {
      "filePath": "core/run-orchestrator",
      "fileName": "index.ts"
    },
    {
      "filePath": "core/run-orchestrator/__tests__",
      "fileName": "bootstrap.test.ts",
      "lineRange": { "start": 44, "end": 75 }
    },
    {
      "filePath": "core/run-orchestrator/__tests__",
      "fileName": "render-step.test.ts",
      "lineRange": { "start": 15, "end": 42 }
    },
    {
      "filePath": "ai-log/question_cropper_v1_1775585265501_1",
      "fileName": "proof-log.md"
    },
    {
      "filePath": "docs/question-cropper-v1",
      "fileName": "PROOF_LOG.md",
      "lineRange": { "start": 447, "end": 646 }
    },
    {
      "filePath": ".",
      "fileName": "package.json",
      "lineRange": { "start": 6, "end": 16 }
    }
  ]
}
